Workbook

Sheet Sheet1
A1: Job Type
A2: Name
A3: Date
A4: District
A5: Township
A6: Payment Method
A7: Road Name
A8: Road Limits
A9: Comments
A10: Length (feet)
A11: Width (feet)
A12: Depth (inches)
... A24: Notes

Sheet Limestone
B1: GENESEE COUNTY ROAD COMMISSION | H1: GENESEE COUNTY ROAD COMMISSION
B2: MAINTENANCE DEPARTMENT | H2: MAINTENANCE DEPARTMENT
B3: ="COST FOR "& UPPER(Sheet1!B1) -> COST FOR | H3: 211 West Oakley Street Flint, Michigan 48503-3995
B4: TOWNSHIP OF | C4: =LEFT(Sheet1!B5, LEN(Sheet1!B5)-9) -> #VALUE! | G4: ="COST FOR "& UPPER(Sheet1!B1) -> COST FOR
B5: ROAD NAME: | C5: =Sheet1!B7 -> 0
B6: LENGTH: | C6: =Sheet1!B10&"' X "&Sheet1!B11&"' X "&Sheet1!B12&"""" -> ' X ' X " | G6: DATE | H6: =Sheet1!B3 -> 0 | J6: TOWNSHIP OF | M6: =C4 -> #VALUE!
B7: TYPE OF WORK: | C7: =Sheet1!B1 -> 0
B8: COMMENTS | C8: =Sheet1!B9 -> 0 | G8: ROAD NAME: | H8: =C5 -> 0
A9: I. Labor | G9: LENGTH: | H9: =C6 -> ' X ' X " | M9: Miles: | N9: =Sheet1!B10/5280 -> 0
A10: LABOR - Regular | C10: QTY | D10: UNIT | E10: UNIT COST | F10: TOTAL | G10: TYPE OF WORK: | H10: =C7 -> 0
A11: =Sheet1!B14 -> 0 | B11: Equipment Operator | C11: =Sheet1!B16 -> 0 | D11: Hr | E11: 32.47 | F11: =A11*C11*E11 -> 0 | G11: ADDITIONAL COMMENTS | H11: *Prices good for the 2025/2026 FY* | K11: Final accounting will be based on actual cost
A12: =Sheet1!B15 -> 0 | B12: Foreman | C12: =Sheet1!B17 -> 0 | D12: Hr | E12: 41.31 | F12: =A12*C12*E12 -> 0 | H12: =C8 -> 0
A13: LABOR - OT | C13: QTY | D13: UNIT | E13: UNIT COST | F13: TOTAL
A14: =Sheet1!B18 -> 0 | B14: Equipment Operator | C14: =Sheet1!B20 -> 0 | D14: Hr | E14: 48.71 | F14: =A14*C14*E14 -> 0 | I14: SUMMARY OF ESTIMATED COST
A15: =Sheet1!B19 -> 0 | B15: Foreman | C15: =Sheet1!B21 -> 0 | D15: Hr | E15: 61.97 | F15: =A15*C15*E15 -> 0 | I15: Estimated Time Needed to Complete Work
C16: Subtotal Days | E16: =Sheet1!B13 -> 0 | F16: =SUM(F11:F15)*K16 -> 0 | J16: Day/Days | K16: =Sheet1!B13 -> 0
A17: Sub Total Man Hours | C17: =(SUM(A11*C11)+(A12*C12)+(A14*C14)+(A15*C15))*K16 -> 0 | D17: Fringe | E17: 1.043569 | F17: =F16*E17 -> 0
A18: Total Labor & Fringe | C18: . | F18: =F16+F17 -> 0 | J18: GRAND TOTAL | K18: =F47 -> 0
A19: II. Equipment
A20: Equipment Description | C20: QTY | D20: UNIT | E20: UNIT COST | F20: TOTAL | I20: Township Participation | K20: =K18*(Sheet1!#REF!/100) -> #REF!
A21: =Sheet1!C26 -> 0 | B21: =Sheet1!B26&" - #"&Sheet1!E26 -> - # | C21: =Sheet1!D26 -> 0 | D21: Hr | E21: =LOOKUP(Sheet1!E26,Table336789101112131415[Equip Number], Table336789101112131415[Sched C/ County/ State]) -> #N/A | F21: =E21*A21*C21 -> #N/A
A22: =Sheet1!C27 -> 0 | B22: =Sheet1!B27&" - #"&Sheet1!E27 -> - # | C22: =Sheet1!D27 -> 0 | D22: Hr | E22: =LOOKUP(Sheet1!E27,Table336789101112131415[Equip Number], Table336789101112131415[Sched C/ County/ State]) -> #N/A | F22: =E22*A22*C22 -> #N/A | I22: GCRC Allocation Funds | K22: =K18*(Sheet1!#REF!/100) -> #REF!
A23: =Sheet1!C28 -> 0 | B23: =Sheet1!B28&" - #"&Sheet1!E28 -> - # | C23: =Sheet1!D28 -> 0 | D23: Hr | E23: =LOOKUP(Sheet1!E28,Table336789101112131415[Equip Number], Table336789101112131415[Sched C/ County/ State]) -> #N/A | F23: =E23*A23*C23 -> #N/A
A24: =Sheet1!C29 -> 0 | B24: =Sheet1!B29&" - #"&Sheet1!E29 -> - # | C24: =Sheet1!D29 -> 0 | D24: Hr | E24: =LOOKUP(Sheet1!E29,Table336789101112131415[Equip Number], Table336789101112131415[Sched C/ County/ State]) -> #N/A | F24: =E24*A24*C24 -> #N/A | I24: Participation by Others | M24: Source: ___________________
A25: =Sheet1!C30 -> 0 | B25: =Sheet1!B30&" - #"&Sheet1!E30 -> - # | C25: =Sheet1!D30 -> 0 | D25: Hr | E25: =LOOKUP(Sheet1!E30,Table336789101112131415[Equip Number], Table336789101112131415[Sched C/ County/ State]) -> #N/A | F25: =E25*A25*C25 -> #N/A
A26: =Sheet1!C31 -> 0 | B26: =Sheet1!B31&" - #"&Sheet1!E31 -> - # | C26: =Sheet1!D31 -> 0 | D26: Hr | E26: =LOOKUP(Sheet1!E31,Table336789101112131415[Equip Number], Table336789101112131415[Sched C/ County/ State]) -> #N/A | F26: =E26*A26*C26 -> #N/A | H26: Community Development Block Grant (CDBG) | K26: Yes | M26: No
A27: =Sheet1!C32 -> 0 | B27: =Sheet1!B32&" - #"&Sheet1!E32 -> - # | C27: =Sheet1!D32 -> 0 | D27: Hr | E27: =LOOKUP(Sheet1!E32,Table336789101112131415[Equip Number], Table336789101112131415[Sched C/ County/ State]) -> #N/A | F27: =E27*A27*C27 -> #N/A
A28: =Sheet1!C33 -> 0 | B28: =Sheet1!B33&" - #"&Sheet1!E33 -> - # | C28: =Sheet1!D33 -> 0 | D28: Hr | E28: =LOOKUP(Sheet1!E33,Table336789101112131415[Equip Number], Table336789101112131415[Sched C/ County/ State]) -> #N/A | F28: =E28*A28*C28 -> #N/A | G28: Please sign below and return to the Maintenance Department, if your Township would like the Genesee County Road
A29: =Sheet1!C34 -> 0 | B29: =Sheet1!B34&" - #"&Sheet1!E34 -> - # | C29: =Sheet1!D34 -> 0 | D29: Hr | E29: =LOOKUP(Sheet1!E34,Table336789101112131415[Equip Number], Table336789101112131415[Sched C/ County/ State]) -> #N/A | F29: =E29*A29*C29 -> #N/A | G29: Commission to proceed with this work. It is agreed that in the event the cost exceeds more than 10% of above
A30: =Sheet1!C35 -> 0 | B30: =Sheet1!B35&" - #"&Sheet1!E35 -> - # | C30: =Sheet1!D35 -> 0 | D30: Hr | E30: =LOOKUP(Sheet1!E35,Table336789101112131415[Equip Number], Table336789101112131415[Sched C/ County/ State]) -> #N/A | F30: =E30*A30*C30 -> #N/A | G30: estimate, the Road Commission will consult with the Township prior to final billing.
A31: =Sheet1!C36 -> 0 | B31: =Sheet1!B36&" - #"&Sheet1!E36 -> - # | C31: =Sheet1!D36 -> 0 | D31: Hr | E31: =LOOKUP(Sheet1!E36,Table336789101112131415[Equip Number], Table336789101112131415[Sched C/ County/ State]) -> #N/A | F31: =E31*A31*C31 -> #N/A
A32: =Sheet1!C37 -> 0 | B32: =Sheet1!B37&" - #"&Sheet1!E37 -> - # | C32: =Sheet1!D37 -> 0 | D32: Hr | E32: =LOOKUP(Sheet1!E37,Table336789101112131415[Equip Number], Table336789101112131415[Sched C/ County/ State]) -> #N/A | F32: =E32*A32*C32 -> #N/A | H32: Township's Board Approval
A33: =Sheet1!C38 -> 0 | B33: =Sheet1!B38&" - #"&Sheet1!E38 -> - # | C33: =Sheet1!D38 -> 0 | D33: Hr | E33: =LOOKUP(Sheet1!E38,Table336789101112131415[Equip Number], Table336789101112131415[Sched C/ County/ State]) -> #N/A | F33: =E33*A33*C33 -> #N/A | J33: Supervisor | N33: Date
A34: =Sheet1!C39 -> 0 | B34: =Sheet1!B39&" - #"&Sheet1!E39 -> - # | C34: =Sheet1!D39 -> 0 | D34: Hr | E34: =LOOKUP(Sheet1!E39,Table336789101112131415[Equip Number], Table336789101112131415[Sched C/ County/ State]) -> #N/A | F34: =E34*A34*C34 -> #N/A | H34: Road Commission's Board Approval
A35: =Sheet1!C40 -> 0 | B35: =Sheet1!B40&" - #"&Sheet1!E40 -> - # | C35: =Sheet1!D40 -> 0 | D35: Hr | E35: =LOOKUP(Sheet1!E40,Table336789101112131415[Equip Number], Table336789101112131415[Sched C/ County/ State]) -> #N/A | F35: =E35*A35*C35 -> #N/A | J35: Chairperson | N35: Date
A36: =Sheet1!C41 -> 0 | B36: =Sheet1!B41&" - #"&Sheet1!E41 -> - # | C36: =Sheet1!D41 -> 0 | D36: Hr | E36: =LOOKUP(Sheet1!E41,Table336789101112131415[Equip Number], Table336789101112131415[Sched C/ County/ State]) -> #N/A | F36: =E36*A36*C36 -> #N/A
A37: =Sheet1!C42 -> 0 | B37: =Sheet1!B42&" - #"&Sheet1!E42 -> - # | C37: =Sheet1!D42 -> 0 | D37: Hr | E37: =LOOKUP(Sheet1!E42,Table336789101112131415[Equip Number], Table336789101112131415[Sched C/ County/ State]) -> #N/A | F37: =E37*A37*C37 -> #N/A | G37: Work Order Number | J37: Work Completed
A38: Sub Total Equipment Rate | F38: {=SUM(IFERROR(F21:F37,0))} -> 0 | L38: District Supervisor | N38: Date
A39: Total Equipment Rate Days | E39: 1 | F39: =F38*K16 -> 0
A40: III. Material | K40: Engineering Dept Fund Verification | N40: Matching Allocation
A41: Material Description | C41: QTY | D41: UNIT | E41: UNIT COST | F41: TOTAL
A42: Tons of Asphalt - 4C | D42: TNS | E42: 74.5 | F42: =E42*C42 -> 0 | K42: Signature | N42: Date
A43: Gallons of Tack | D43: GA | E43: 6.5 | F43: =E43*C43 -> 0 | K43: Balance of Available Funds | N43: $
A44: Ace Contracted Services | D44: EA | F44: =E44*C44 -> 0
A45: Total Material | F45: =SUM(F42:F44) -> 0
B47: TOTAL PROJECT COST | F47: =F45+F39+F18 -> 0
D48: Date: | E48: Prepared by:
D49: =Sheet1!B3 -> 0 | F49: =Sheet1!B2 -> 0

Sheet Equipment Rates
A1: Genesee County Road Commission (FA- Specification and Rentals) 2026
A2: EQUIPMENT | F2: 2026 Hourly Rate | I2: 2025 Comparison
A3: Equip Number | B3: Description | C3: Model Year | D3: Make | E3: Model / Series | F3: Sched C/ County/ State | G3: W/Radio | H3: Column1 | I3: 2025 Rate | J3: 2025/26 Variance
A4: 100 | B4: Drone | C4: 2020 | D4: Matrice | E4: 210 V2 | F4: 10.75 | I4: 10.06 | J4: =Table336789101112131415[[#This Row],[Sched C/ County/ State]]-Table336789101112131415[[#This Row],[2025 Rate]] -> 0.69
A5: 101 | B5: Trimble S5 3" Robotic & TSC5 System | C5: 2021 | D5: Trimble | E5: TCS5 System | F5: 8.11 | I5: 7.59 | J5: =Table336789101112131415[[#This Row],[Sched C/ County/ State]]-Table336789101112131415[[#This Row],[2025 Rate]] -> 0.52
A6: 106 | B6: Envirosight Pole Camera | C6: 2021 | D6: Envirosight | F6: 16.27 | I6: 15.23 | J6: =Table336789101112131415[[#This Row],[Sched C/ County/ State]]-Table336789101112131415[[#This Row],[2025 Rate]] -> 1.04
A7: 309 | B7: Hot Patcher (Lease) | C7: 2017 | D7: KM International | E7: KM800TEDD | F7: 47.75 | I7: 44.68 | J7: =Table336789101112131415[[#This Row],[Sched C/ County/ State]]-Table336789101112131415[[#This Row],[2025 Rate]] -> 3.07
A8: 314 | B8: Liquid Spray System - Demo | C8: 2002 | D8: Force America | E8: SSC5100 | F8: 3.05 | I8: 2.85 | J8: =Table336789101112131415[[#This Row],[Sched C/ County/ State]]-Table336789101112131415[[#This Row],[2025 Rate]] -> 0.2
A9: 315 | B9: Anti-icing Unit 1250 Gal Tank - Demo | C9: 2002 | D9: Force America | E9: FA-1250-3L | F9: 20.91 | I9: 19.57 | J9: =Table336789101112131415[[#This Row],[Sched C/ County/ State]]-Table336789101112131415[[#This Row],[2025 Rate]] -> 1.34
A10: 316 | B10: Sign Truck | C10: 1993 | D10: International | E10: 4900 | F10: 33.4 | I10: 30.99 | J10: =Table336789101112131415[[#This Row],[Sched C/ County/ State]]-Table336789101112131415[[#This Row],[2025 Rate]] -> 2.41
A11: 317 | B11: Post Puller | F11: 1.2 | I11: 1.12 | J11: =Table336789101112131415[[#This Row],[Sched C/ County/ State]]-Table336789101112131415[[#This Row],[2025 Rate]] -> 0.08
A12: 318 | B12: Boom | C12: 1993 | D12: Versalift | E12: VST40001 | F12: 18.04 | I12: 16.88 | J12: =Table336789101112131415[[#This Row],[Sched C/ County/ State]]-Table336789101112131415[[#This Row],[2025 Rate]] -> 1.16
A13: 401 | B13: Global Positioning System | C13: 2010 | D13: Teletrac | E13: TM450 | F13: 0.78 | I13: 0.73 | J13: =Table336789101112131415[[#This Row],[Sched C/ County/ State]]-Table336789101112131415[[#This Row],[2025 Rate]] -> 0.05
A14: 402 | B14: Global Positioning System | C14: 2010 | D14: Teletrac | E14: TM450 | F14: 0.78 | I14: 0.73 | J14: =Table336789101112131415[[#This Row],[Sched C/ County/ State]]-Table336789101112131415[[#This Row],[2025 Rate]] -> 0.05
A15: 403 | B15: Global Positioning System | C15: 2010 | D15: Teletrac | E15: TM450 | F15: 0.78 | I15: 0.73 | J15: =Table336789101112131415[[#This Row],[Sched C/ County/ State]]-Table336789101112131415[[#This Row],[2025 Rate]] -> 0.05
A16: 404 | B16: Global Positioning System | C16: 2010 | D16: Teletrac | E16: TM450 | F16: 0.78 | I16: 0.73 | J16: =Table336789101112131415[[#This Row],[Sched C/ County/ State]]-Table336789101112131415[[#This Row],[2025 Rate]] -> 0.05
A17: 405 | B17: Global Positioning System | C17: 2010 | D17: Teletrac | E17: TM450 | F17: 0.78 | I17: 0.73 | J17: =Table336789101112131415[[#This Row],[Sched C/ County/ State]]-Table336789101112131415[[#This Row],[2025 Rate]] -> 0.05
A18: 406 | B18: Global Positioing System | C18: 2010 | D18: Teletrac | E18: TM450J | F18: 0.78 | I18: 0.73 | J18: =Table336789101112131415[[#This Row],[Sched C/ County/ State]]-Table336789101112131415[[#This Row],[2025 Rate]] -> 0.05
A19: 407 | B19: Global Positioning System | C19: 2010 | D19: Teletrac | E19: TM450 | F19: 0.78 | I19: 0.73 | J19: =Table336789101112131415[[#This Row],[Sched C/ County/ State]]-Table336789101112131415[[#This Row],[2025 Rate]] -> 0.05
A20: 408 | B20: Global Positioning System | C20: 2010 | D20: Teletrac | E20: TM450 | F20: 0.78 | I20: 0.73 | J20: =Table336789101112131415[[#This Row],[Sched C/ County/ State]]-Table336789101112131415[[#This Row],[2025 Rate]] -> 0.05
A21: 409 | B21: Global Positioning System | C21: 2010 | D21: Teletrac | E21: TM450 | F21: 0.78 | I21: 0.73 | J21: =Table336789101112131415[[#This Row],[Sched C/ County/ State]]-Table336789101112131415[[#This Row],[2025 Rate]] -> 0.05
A22: 417 | B22: 20" Chainsaw | C22: 2017 | D22: Husqvarna | E22: Rancher455 | F22: 6.98 | I22: 6.53 | J22: =Table336789101112131415[[#This Row],[Sched C/ County/ State]]-Table336789101112131415[[#This Row],[2025 Rate]] -> 0.45
A23: 419 | B23: 24" Chainsaw | C23: 2017 | D23: Husqvarna | E23: 365 | F23: 6.98 | I23: 6.53 | J23: =Table336789101112131415[[#This Row],[Sched C/ County/ State]]-Table336789101112131415[[#This Row],[2025 Rate]] -> 0.45
A24: 424 | B24: 14" Chainsaw | C24: 2017 | D24: Stihl | E24: MS193T | F24: 4.74 | I24: 4.44 | J24: =Table336789101112131415[[#This Row],[Sched C/ County/ State]]-Table336789101112131415[[#This Row],[2025 Rate]] -> 0.3
A25: 427 | B25: Global Positioning System | C25: 2008 | D25: Teletrac | E25: 700-0100 TM2 | F25: 0.78 | I25: 0.73 | J25: =Table336789101112131415[[#This Row],[Sched C/ County/ State]]-Table336789101112131415[[#This Row],[2025 Rate]] -> 0.05
A26: 431 | B26: Global Positioning System | C26: 2008 | D26: Teletrac | E26: 700-0100-TM2 | F26: 0.78 | I26: 0.73 | J26: =Table336789101112131415[[#This Row],[Sched C/ County/ State]]-Table336789101112131415[[#This Row],[2025 Rate]] -> 0.05
A27: 432 | B27: Global Positioning System | C27: 2010 | D27: Teletrac | E27: TM450 | F27: 0.78 | I27: 0.73 | J27: =Table336789101112131415[[#This Row],[Sched C/ County/ State]]-Table336789101112131415[[#This Row],[2025 Rate]] -> 0.05
A28: 433 | B28: Global Positioning System | C28: 2010 | D28: Teletrac | E28: TM450 | F28: 0.78 | I28: 0.73 | J28: =Table336789101112131415[[#This Row],[Sched C/ County/ State]]-Table336789101112131415[[#This Row],[2025 Rate]] -> 0.05
A29: 434 | B29: Global Positioning System | C29: 2010 | D29: Teletrac | E29: TM450 | F29: 0.78 | I29: 0.73 | J29: =Table336789101112131415[[#This Row],[Sched C/ County/ State]]-Table336789101112131415[[#This Row],[2025 Rate]] -> 0.05
A30: 435 | B30: Global Positioning System | C30: 2010 | D30: Teletrac | E30: TM450 | F30: 0.78 | I30: 0.73 | J30: =Table336789101112131415[[#This Row],[Sched C/ County/ State]]-Table336789101112131415[[#This Row],[2025 Rate]] -> 0.05
A31: 436 | B31: Global Positioning System | C31: 2010 | D31: Teletrac | E31: TM450 | F31: 0.78 | I31: 0.73 | J31: =Table336789101112131415[[#This Row],[Sched C/ County/ State]]-Table336789101112131415[[#This Row],[2025 Rate]] -> 0.05
A32: 437 | B32: Global Positioning System | C32: 2010 | D32: Teletrac | E32: TM450 | F32: 0.78 | I32: 0.73 | J32: =Table336789101112131415[[#This Row],[Sched C/ County/ State]]-Table336789101112131415[[#This Row],[2025 Rate]] -> 0.05
A33: 438 | B33: Global Positioning System | C33: 2010 | D33: Teletrac | E33: TM450 | F33: 0.78 | I33: 0.73 | J33: =Table336789101112131415[[#This Row],[Sched C/ County/ State]]-Table336789101112131415[[#This Row],[2025 Rate]] -> 0.05
A34: 439 | B34: Salt Calibrator | C34: 2018 | D34: Scale Tec | E34: IV-PSF | F34: 6.49 | I34: 6.07 | J34: =Table336789101112131415[[#This Row],[Sched C/ County/ State]]-Table336789101112131415[[#This Row],[2025 Rate]] -> 0.42
A35: 440 | B35: Distance Meter | C35: 2017 | D35: FastMeasure | E35: FM-GPS | F35: 0.1 | I35: 0.09 | J35: =Table336789101112131415[[#This Row],[Sched C/ County/ State]]-Table336789101112131415[[#This Row],[2025 Rate]] -> 0.01
... A53: 462 | B53: De-Icing Liquid Tank | C53: 2018 | D53: Monroe | E53: DCDFV-11.510067 | F53: 32.76 | I53: 30.66 | J53: =Table336789101112131415[[#This Row],[Sched C/ County/ State]]-Table336789101112131415[[#This Row],[2025 Rate]] -> 2.1
A54: 463 | B54: De-Icing Pump | C54: 2018 | D54: Banjo | E54: 200 | F54: 6.98 | I54: 6.48 | J54: =Table336789101112131415[[#This Row],[Sched C/ County/ State]]-Table336789101112131415[[#This Row],[2025 Rate]] -> 0.5
A55: 464 | B55: De-Icing Pump | C55: 2018 | D55: Banjo | E55: 200 | F55: 6.98 | I55: 6.48 | J55: =Table336789101112131415[[#This Row],[Sched C/ County/ State]]-Table336789101112131415[[#This Row],[2025 Rate]] -> 0.5
A56: 465 | B56: Patching Shelf | C56: 2018 | D56: Own Make | F56: 0.59 | I56: 0.55 | J56: =Table336789101112131415[[#This Row],[Sched C/ County/ State]]-Table336789101112131415[[#This Row],[2025 Rate]] -> 0.04
A57: 466 | B57: De-Icing Liquid Tank | C57: 2018 | D57: Monroe | E57: DCDFV-11.510067 | F57: 32.76 | I57: 30.66 | J57: =Table336789101112131415[[#This Row],[Sched C/ County/ State]]-Table336789101112131415[[#This Row],[2025 Rate]] -> 2.1
A58: 467 | B58: Rotary Screw Compressor | C58: 2018 | D58: Atlas Copco | E58: GA15P | F58: 6.47 | I58: 6.05 | J58: =Table336789101112131415[[#This Row],[Sched C/ County/ State]]-Table336789101112131415[[#This Row],[2025 Rate]] -> 0.42
A59: 468 | B59: Rotary Screw Compressor | C59: 2019 | D59: VMAC | E59: VR70 | F59: 5.12 | I59: 4.75 | J59: =Table336789101112131415[[#This Row],[Sched C/ County/ State]]-Table336789101112131415[[#This Row],[2025 Rate]] -> 0.37
A60: 469 | B60: Comb Catch Basin/Sewer Jet | C60: 2019 | D60: Vactor | E60: 2115I824-100A | F60: 50.11 | I60: 46.89 | J60: =Table336789101112131415[[#This Row],[Sched C/ County/ State]]-Table336789101112131415[[#This Row],[2025 Rate]] -> 3.22
A61: 470 | B61: Traffic Counter | C61: 2018 | D61: Delta | E61: NT | F61: 0.38 | I61: 0.36 | J61: =Table336789101112131415[[#This Row],[Sched C/ County/ State]]-Table336789101112131415[[#This Row],[2025 Rate]] -> 0.02
A62: 471 | B62: Traffic Counter | C62: 2018 | D62: Delta | E62: NT | F62: 0.38 | I62: 0.36 | J62: =Table336789101112131415[[#This Row],[Sched C/ County/ State]]-Table336789101112131415[[#This Row],[2025 Rate]] -> 0.02
A63: 472 | B63: Traffic Counter | C63: 2018 | D63: Delta | E63: NT | F63: 0.38 | I63: 0.36 | J63: =Table336789101112131415[[#This Row],[Sched C/ County/ State]]-Table336789101112131415[[#This Row],[2025 Rate]] -> 0.02
A64: 473 | B64: Traffic Counter | C64: 2018 | D64: Delta | E64: NT | F64: 0.38 | I64: 0.36 | J64: =Table336789101112131415[[#This Row],[Sched C/ County/ State]]-Table336789101112131415[[#This Row],[2025 Rate]] -> 0.02
A65: 474 | B65: Pre-Wetting System | C65: 2019 | D65: Monroe | F65: 3.05 | I65: 2.85 | J65: =Table336789101112131415[[#This Row],[Sched C/ County/ State]]-Table336789101112131415[[#This Row],[2025 Rate]] -> 0.2
A66: 475 | B66: Traffic Counter | C66: 2018 | D66: Delta | E66: NT | F66: 0.38 | I66: 0.36 | J66: =Table336789101112131415[[#This Row],[Sched C/ County/ State]]-Table336789101112131415[[#This Row],[2025 Rate]] -> 0.02
A67: 476 | B67: Traffic Counter | C67: 2018 | D67: Delta | E67: NT | F67: 0.38 | I67: 0.36 | J67: =Table336789101112131415[[#This Row],[Sched C/ County/ State]]-Table336789101112131415[[#This Row],[2025 Rate]] -> 0.02
A68: 477 | B68: Pre-Wetting System | C68: 2019 | D68: Flo-Torq | E68: 2@110"=250 gal | F68: 3.05 | I68: 2.85 | J68: =Table336789101112131415[[#This Row],[Sched C/ County/ State]]-Table336789101112131415[[#This Row],[2025 Rate]] -> 0.2
A69: 478 | B69: Pre-Wetting System | C69: 2019 | D69: Monroe | F69: 3.05 | I69: 2.85 | J69: =Table336789101112131415[[#This Row],[Sched C/ County/ State]]-Table336789101112131415[[#This Row],[2025 Rate]] -> 0.2
A70: 479 | B70: Pre-Wetting System | C70: 2019 | F70: 3.05 | I70: 2.85 | J70: =Table336789101112131415[[#This Row],[Sched C/ County/ State]]-Table336789101112131415[[#This Row],[2025 Rate]] -> 0.2
A71: 480 | B71: Cat Scale & Printer | C71: 2019 | D71: Mi Cat | E71: Load Rite Scale | F71: 1.63 | I71: 1.51 | J71: =Table336789101112131415[[#This Row],[Sched C/ County/ State]]-Table336789101112131415[[#This Row],[2025 Rate]] -> 0.12
A72: 482 | B72: Compressor | C72: 2024 | D72: SpeedAire | E72: 6.5HP | F72: 5.12 | I72: 4.75 | J72: =Table336789101112131415[[#This Row],[Sched C/ County/ State]]-Table336789101112131415[[#This Row],[2025 Rate]] -> 0.37
A73: 483 | B73: Compressor | C73: 2020 | D73: SpeedAire | E73: 4NB84 | F73: 2.45 | I73: 2.29 | J73: =Table336789101112131415[[#This Row],[Sched C/ County/ State]]-Table336789101112131415[[#This Row],[2025 Rate]] -> 0.16
A74: 484 | B74: Arrow | C74: 2019 | D74: Code 3 | E74: Narrow Stick | F74: 0.57 | I74: 0.53 | J74: =Table336789101112131415[[#This Row],[Sched C/ County/ State]]-Table336789101112131415[[#This Row],[2025 Rate]] -> 0.04
A75: 485 | B75: 14" Cut Off Saw | C75: 2020 | D75: Husqvarna | E75: K770 | F75: 20.43 | I75: 19.12 | J75: =Table336789101112131415[[#This Row],[Sched C/ County/ State]]-Table336789101112131415[[#This Row],[2025 Rate]] -> 1.31
A76: 486 | B76: 14" Cut Off Saw | C76: 2020 | D76: Husqvarna | E76: K770 | F76: 20.43 | I76: 19.12 | J76: =Table336789101112131415[[#This Row],[Sched C/ County/ State]]-Table336789101112131415[[#This Row],[2025 Rate]] -> 1.31
A77: 487 | B77: Pole Saw | C77: 2020 | D77: Stihl | E77: HT131 | F77: 5.9 | I77: 5.52 | J77: =Table336789101112131415[[#This Row],[Sched C/ County/ State]]-Table336789101112131415[[#This Row],[2025 Rate]] -> 0.38
A78: 488 | B78: Load Rite Scale & Printer | C78: 2019 | D78: John Deere | E78: Load Rite Scale | F78: 1.63 | I78: 1.51 | J78: =Table336789101112131415[[#This Row],[Sched C/ County/ State]]-Table336789101112131415[[#This Row],[2025 Rate]] -> 0.12
A79: 489 | B79: Load Rite Scale & Printer | C79: 2019 | D79: Caterpillar | E79: Load Rite Scale | F79: 1.63 | I79: 1.51 | J79: =Table336789101112131415[[#This Row],[Sched C/ County/ State]]-Table336789101112131415[[#This Row],[2025 Rate]] -> 0.12
A80: 490 | B80: Automatic Slope Control System | C80: 2014 | D80: Caterpillar | F80: 8.82 | I80: 8.25 | J80: =Table336789101112131415[[#This Row],[Sched C/ County/ State]]-Table336789101112131415[[#This Row],[2025 Rate]] -> 0.57
A81: 491 | B81: Automatic Slope Control System | C81: 2015 | D81: Caterpillar | F81: 8.82 | I81: 8.25 | J81: =Table336789101112131415[[#This Row],[Sched C/ County/ State]]-Table336789101112131415[[#This Row],[2025 Rate]] -> 0.57
A82: 492 | B82: Traffic Counter | C82: 2016 | D82: Delta | F82: 0.38 | I82: 0.36 | J82: =Table336789101112131415[[#This Row],[Sched C/ County/ State]]-Table336789101112131415[[#This Row],[2025 Rate]] -> 0.02
A83: 493 | B83: Traffic Counter | C83: 2016 | D83: Delta | F83: 0.38 | I83: 0.34 | J83: =Table336789101112131415[[#This Row],[Sched C/ County/ State]]-Table336789101112131415[[#This Row],[2025 Rate]] -> 0.04
A84: 494 | B84: Traffic Counter | C84: 2016 | D84: Delta | F84: 0.38 | I84: 0.36 | J84: =Table336789101112131415[[#This Row],[Sched C/ County/ State]]-Table336789101112131415[[#This Row],[2025 Rate]] -> 0.02
A85: 495 | B85: Traffic Counter | C85: 2016 | D85: Delta | F85: 0.38 | I85: 0.36 | J85: =Table336789101112131415[[#This Row],[Sched C/ County/ State]]-Table336789101112131415[[#This Row],[2025 Rate]] -> 0.02
A86: 496 | B86: Traffic Counter | C86: 2016 | D86: Delta | F86: 0.38 | I86: 0.36 | J86: =Table336789101112131415[[#This Row],[Sched C/ County/ State]]-Table336789101112131415[[#This Row],[2025 Rate]] -> 0.02
A87: 497 | B87: Traffic Counter | C87: 2016 | D87: Delta | F87: 0.38 | I87: 0.36 | J87: =Table336789101112131415[[#This Row],[Sched C/ County/ State]]-Table336789101112131415[[#This Row],[2025 Rate]] -> 0.02
A88: 498 | B88: Brine Maker | C88: 2018 | D88: Cargill | E88: Accubrine NXT | F88: 47.8 | I88: 44.06 | J88: =Table336789101112131415[[#This Row],[Sched C/ County/ State]]-Table336789101112131415[[#This Row],[2025 Rate]] -> 3.74
A89: 499 | B89: Automatic Slope Control System | C89: 2014 | D89: Caterpillar | F89: 8.82 | I89: 8.25 | J89: =Table336789101112131415[[#This Row],[Sched C/ County/ State]]-Table336789101112131415[[#This Row],[2025 Rate]] -> 0.57
A90: 500 | B90: SUV - All Wheel Drive | C90: 2020 | D90: GMC | E90: Terrain AWD | F90: 15.13 | G90: =Table336789101112131415[[#This Row],[Sched C/ County/ State]]+0.3 -> 15.43 | I90: 14.16 | J90: =Table336789101112131415[[#This Row],[Sched C/ County/ State]]-Table336789101112131415[[#This Row],[2025 Rate]] -> 0.97
A91: 525 | B91: Car | C91: 2012 | D91: Chevrolet | E91: Impala | F91: 16.07 | G91: =Table336789101112131415[[#This Row],[Sched C/ County/ State]]+0.3 -> 16.37 | I91: 14.91 | J91: =Table336789101112131415[[#This Row],[Sched C/ County/ State]]-Table336789101112131415[[#This Row],[2025 Rate]] -> 1.16
A92: 527 | B92: SUV - All Wheel Drive | C92: 2017 | D92: GMC | E92: Terrain | F92: 15.13 | G92: =Table336789101112131415[[#This Row],[Sched C/ County/ State]]+0.3 -> 15.43 | I92: 14.16 | J92: =Table336789101112131415[[#This Row],[Sched C/ County/ State]]-Table336789101112131415[[#This Row],[2025 Rate]] -> 0.97
A93: 528 | B93: SUV - All Wheel Drive | C93: 2017 | D93: GMC | E93: Terrain | F93: 15.13 | G93: =Table336789101112131415[[#This Row],[Sched C/ County/ State]]+0.3 -> 15.43 | I93: 14.16 | J93: =Table336789101112131415[[#This Row],[Sched C/ County/ State]]-Table336789101112131415[[#This Row],[2025 Rate]] -> 0.97
A94: 561 | B94: Road Widener | C94: 2019 | D94: Road Widener | E94: WT-SSL | F94: 60.18 | I94: 56.32 | J94: =Table336789101112131415[[#This Row],[Sched C/ County/ State]]-Table336789101112131415[[#This Row],[2025 Rate]] -> 3.86
A95: 562 | B95: Road Widener | C95: 2023 | D95: Road Widener | E95: SPF-8 | F95: 60.18 | I95: 56.32 | J95: =Table336789101112131415[[#This Row],[Sched C/ County/ State]]-Table336789101112131415[[#This Row],[2025 Rate]] -> 3.86
A96: 563 | B96: Autocrane | C96: 2019 | D96: Crane | E96: 3203 PRX | F96: 18.04 | I96: 16.88 | J96: =Table336789101112131415[[#This Row],[Sched C/ County/ State]]-Table336789101112131415[[#This Row],[2025 Rate]] -> 1.16
A97: 571 | B97: Patching Shelf | C97: 2018 | D97: Monroe | E97: 00016220-B | F97: 0.59 | I97: 0.55 | J97: =Table336789101112131415[[#This Row],[Sched C/ County/ State]]-Table336789101112131415[[#This Row],[2025 Rate]] -> 0.04
A98: 577 | B98: Patching Shelf | C98: 2019 | D98: Monroe | E98: SS | F98: 0.59 | I98: 0.55 | J98: =Table336789101112131415[[#This Row],[Sched C/ County/ State]]-Table336789101112131415[[#This Row],[2025 Rate]] -> 0.04
A99: 617 | B99: Pick up Truck | C99: 2009 | D99: Chevrolet | E99: 2500HD | F99: 13.84 | G99: =Table336789101112131415[[#This Row],[Sched C/ County/ State]]+0.3 -> 14.14 | I99: 12.95 | J99: =Table336789101112131415[[#This Row],[Sched C/ County/ State]]-Table336789101112131415[[#This Row],[2025 Rate]] -> 0.89
A100: 619 | B100: 1/2 Ton Pick-up Truck | C100: 2010 | D100: GMC | E100: Sierra 1500 | F100: 13.84 | G100: =Table336789101112131415[[#This Row],[Sched C/ County/ State]]+0.3 -> 14.14 | I100: 12.95 | J100: =Table336789101112131415[[#This Row],[Sched C/ County/ State]]-Table336789101112131415[[#This Row],[2025 Rate]] -> 0.89
A101: 621 | B101: 1/2 Ton Pick-up Truck | C101: 2010 | D101: GMC | E101: Sierra 1500 | F101: 13.84 | G101: =Table336789101112131415[[#This Row],[Sched C/ County/ State]]+0.3 -> 14.14 | I101: 12.95 | J101: =Table336789101112131415[[#This Row],[Sched C/ County/ State]]-Table336789101112131415[[#This Row],[2025 Rate]] -> 0.89
A102: 623 | B102: 1/2 Ton Pick-up Truck | C102: 2010 | D102: GMC | E102: Sierra 1500 | F102: 13.84 | G102: =Table336789101112131415[[#This Row],[Sched C/ County/ State]]+0.3 -> 14.14 | I102: 12.95 | J102: =Table336789101112131415[[#This Row],[Sched C/ County/ State]]-Table336789101112131415[[#This Row],[2025 Rate]] -> 0.89
A103: 624 | B103: 1/2 Ton Pick-up Truck | C103: 2010 | D103: GMC | E103: Sierra 1500 | F103: 13.84 | G103: =Table336789101112131415[[#This Row],[Sched C/ County/ State]]+0.3 -> 14.14 | I103: 12.95 | J103: =Table336789101112131415[[#This Row],[Sched C/ County/ State]]-Table336789101112131415[[#This Row],[2025 Rate]] -> 0.89
A104: 634 | B104: 1/2 Ton Pick up Truck | C104: 2011 | D104: GMC | E104: Sierra 1500 | F104: 13.84 | G104: =Table336789101112131415[[#This Row],[Sched C/ County/ State]]+0.3 -> 14.14 | I104: 12.95 | J104: =Table336789101112131415[[#This Row],[Sched C/ County/ State]]-Table336789101112131415[[#This Row],[2025 Rate]] -> 0.89
A105: 640 | B105: 1/2 Ton Pick up Truck | C105: 2013 | D105: GMC | E105: Sierra 1500 | F105: 13.84 | G105: =Table336789101112131415[[#This Row],[Sched C/ County/ State]]+0.3 -> 14.14 | I105: 12.95 | J105: =Table336789101112131415[[#This Row],[Sched C/ County/ State]]-Table336789101112131415[[#This Row],[2025 Rate]] -> 0.89
A106: 642 | B106: 1/2 Ton Pick up Truck | C106: 2013 | D106: GMC | E106: Sierra | F106: 13.84 | G106: =Table336789101112131415[[#This Row],[Sched C/ County/ State]]+0.3 -> 14.14 | I106: 12.95 | J106: =Table336789101112131415[[#This Row],[Sched C/ County/ State]]-Table336789101112131415[[#This Row],[2025 Rate]] -> 0.89
A107: 644 | B107: Pickup Truck | C107: 2016 | D107: GMC | E107: Sierra 2500 HD | F107: 13.84 | G107: =Table336789101112131415[[#This Row],[Sched C/ County/ State]]+0.3 -> 14.14 | I107: 12.95 | J107: =Table336789101112131415[[#This Row],[Sched C/ County/ State]]-Table336789101112131415[[#This Row],[2025 Rate]] -> 0.89
A108: 645 | B108: Pickup Truck | C108: 2016 | D108: GMC | E108: Sierra 1500 | F108: 15.13 | G108: =Table336789101112131415[[#This Row],[Sched C/ County/ State]]+0.3 -> 15.43 | I108: 14.16 | J108: =Table336789101112131415[[#This Row],[Sched C/ County/ State]]-Table336789101112131415[[#This Row],[2025 Rate]] -> 0.97
A109: 646 | B109: Pickup Truck | C109: 2016 | D109: GMC | E109: Sierra 1500 | F109: 15.13 | G109: =Table336789101112131415[[#This Row],[Sched C/ County/ State]]+0.3 -> 15.43 | I109: 14.16 | J109: =Table336789101112131415[[#This Row],[Sched C/ County/ State]]-Table336789101112131415[[#This Row],[2025 Rate]] -> 0.97
A110: 647 | B110: Pickup Truck | C110: 2016 | D110: GMC | E110: Sierra 1500 | F110: 15.13 | G110: =Table336789101112131415[[#This Row],[Sched C/ County/ State]]+0.3 -> 15.43 | I110: 14.16 | J110: =Table336789101112131415[[#This Row],[Sched C/ County/ State]]-Table336789101112131415[[#This Row],[2025 Rate]] -> 0.97
... A155: 693 | B155: Pick up - 4WD Double Cab | C155: 2024 | D155: GMC | E155: Sierra 1500 | F155: 15.13 | G155: =Table336789101112131415[[#This Row],[Sched C/ County/ State]]+0.3 -> 15.43 | I155: 14.16 | J155: =Table336789101112131415[[#This Row],[Sched C/ County/ State]]-Table336789101112131415[[#This Row],[2025 Rate]] -> 0.97
A156: 727 | B156: Road Watch | F156: 0.1 | I156: 0.09 | J156: =Table336789101112131415[[#This Row],[Sched C/ County/ State]]-Table336789101112131415[[#This Row],[2025 Rate]] -> 0.01
A157: 731 | B157: Road Watch | F157: 0.1 | I157: 0.09 | J157: =Table336789101112131415[[#This Row],[Sched C/ County/ State]]-Table336789101112131415[[#This Row],[2025 Rate]] -> 0.01
A158: 732 | B158: Road Watch | F158: 0.1 | I158: 0.09 | J158: =Table336789101112131415[[#This Row],[Sched C/ County/ State]]-Table336789101112131415[[#This Row],[2025 Rate]] -> 0.01
A159: 733 | B159: Road Watch | F159: 0.1 | I159: 0.09 | J159: =Table336789101112131415[[#This Row],[Sched C/ County/ State]]-Table336789101112131415[[#This Row],[2025 Rate]] -> 0.01
A160: 734 | B160: Road Watch | F160: 0.1 | I160: 0.09 | J160: =Table336789101112131415[[#This Row],[Sched C/ County/ State]]-Table336789101112131415[[#This Row],[2025 Rate]] -> 0.01
A161: 735 | B161: Road Watch | F161: 0.1 | I161: 0.09 | J161: =Table336789101112131415[[#This Row],[Sched C/ County/ State]]-Table336789101112131415[[#This Row],[2025 Rate]] -> 0.01
...
